LICENSE
MANIFEST.in
README.md
requirements-py2.txt
requirements.txt
setup.py
atomic_reactor/__init__.py
atomic_reactor/api.py
atomic_reactor/build.py
atomic_reactor/buildimage.py
atomic_reactor/constants.py
atomic_reactor/core.py
atomic_reactor/inner.py
atomic_reactor/koji_util.py
atomic_reactor/outer.py
atomic_reactor/plugin.py
atomic_reactor/pulp_util.py
atomic_reactor/source.py
atomic_reactor/util.py
atomic_reactor/version.py
atomic_reactor.egg-info/PKG-INFO
atomic_reactor.egg-info/SOURCES.txt
atomic_reactor.egg-info/dependency_links.txt
atomic_reactor.egg-info/entry_points.txt
atomic_reactor.egg-info/requires.txt
atomic_reactor.egg-info/top_level.txt
atomic_reactor/cli/__init__.py
atomic_reactor/cli/main.py
atomic_reactor/plugins/__init__.py
atomic_reactor/plugins/build_docker_api.py
atomic_reactor/plugins/build_orchestrate_build.py
atomic_reactor/plugins/exit_delete_from_registry.py
atomic_reactor/plugins/exit_koji_import.py
atomic_reactor/plugins/exit_koji_promote.py
atomic_reactor/plugins/exit_koji_tag_build.py
atomic_reactor/plugins/exit_pulp_publish.py
atomic_reactor/plugins/exit_remove_built_image.py
atomic_reactor/plugins/exit_sendmail.py
atomic_reactor/plugins/exit_store_logs_to_file.py
atomic_reactor/plugins/exit_store_metadata_in_osv3.py
atomic_reactor/plugins/input_env.py
atomic_reactor/plugins/input_osv3.py
atomic_reactor/plugins/input_path.py
atomic_reactor/plugins/post_compress.py
atomic_reactor/plugins/post_cp_built_image_to_nfs.py
atomic_reactor/plugins/post_fetch_worker_metadata.py
atomic_reactor/plugins/post_group_manifests.py
atomic_reactor/plugins/post_import_image.py
atomic_reactor/plugins/post_koji_upload.py
atomic_reactor/plugins/post_pulp_pull.py
atomic_reactor/plugins/post_pulp_sync.py
atomic_reactor/plugins/post_pulp_tag.py
atomic_reactor/plugins/post_push_to_pulp.py
atomic_reactor/plugins/post_rpmqa.py
atomic_reactor/plugins/post_tag_and_push.py
atomic_reactor/plugins/post_tag_by_labels.py
atomic_reactor/plugins/post_tag_from_config.py
atomic_reactor/plugins/pre_add_dockerfile.py
atomic_reactor/plugins/pre_add_filesystem.py
atomic_reactor/plugins/pre_add_help.py
atomic_reactor/plugins/pre_add_labels_in_df.py
atomic_reactor/plugins/pre_add_yum_repo.py
