Metadata-Version: 1.0
Name: atomic-reactor
Version: 1.6.26.3
Summary: Python library with command line interface for building docker images.
Home-page: https://github.com/projectatomic/atomic-reactor
Author: Red Hat, Inc.
Author-email: atomic-devel@projectatomic.io
License: BSD
Platform: UNKNOWN
